README.md
setup.cfg
setup.py
rpi_radio_alarm.egg-info/PKG-INFO
rpi_radio_alarm.egg-info/SOURCES.txt
rpi_radio_alarm.egg-info/dependency_links.txt
rpi_radio_alarm.egg-info/requires.txt
rpi_radio_alarm.egg-info/top_level.txt
rpiradioalarm/ApiHelper.py
rpiradioalarm/RpiArgumentParser.py
rpiradioalarm/RpiResponseParser.py
rpiradioalarm/__init__.py
rpiradioalarm/constants.py