Metadata-Version: 2.1
Name: rpi-radio-alarm
Version: 0.3.5
Summary: rpi-radio-alarm library
Home-page: UNKNOWN
Author: bb4L
Author-email: 39266013+bb4L@users.noreply.github.com
License: LGPLv3
Project-URL: Source Code, https://github.com/bb4L/rpi-radio-alarm-pip
Keywords: Raspberry Pi,radio,alarm
Platform: UNKNOWN
Classifier: Development Status :: 4 - Beta
Classifier: Intended Audience :: Developers
Classifier: Topic :: Software Development
Classifier: License :: OSI Approved :: GNU Lesser General Public License v3 (LGPLv3)
Classifier: Programming Language :: Python :: 3
Classifier: Programming Language :: Python :: 3.6
